LICENSE.txt
setup.py
ST4/__init__.py
ST4.egg-info/PKG-INFO
ST4.egg-info/SOURCES.txt
ST4.egg-info/dependency_links.txt
ST4.egg-info/requires.txt
ST4.egg-info/top_level.txt