Metadata-Version: 2.2
Name: ST4
Version: 22
Summary: null
Author: HUSSAIN
Author-email: reco9678785@gmail.com
Classifier: Programming Language :: Python :: 3
Classifier: License :: OSI Approved :: MIT License
Classifier: Operating System :: OS Independent
Requires-Python: >=3.6
License-File: LICENSE.txt
Requires-Dist: user_agent
Requires-Dist: requests
Requires-Dist: MedoSigner
Requires-Dist: pycryptodome
Dynamic: author
Dynamic: author-email
Dynamic: classifier
Dynamic: requires-dist
Dynamic: requires-python
Dynamic: summary
